{
  "report_date": "2026-05-14",
  "executive_summary": "Cannes Film Festival is dominating media with Dior Beauty Suite and luxury brand activations — act on the glamour-meets-outdoors narrative today. Preakness Stakes is 3 days out — equestrian content window is open right now.",
  "cobas_daughter_spotlight": {
    "top_opportunity": "Preakness Stakes in 3 days: post equestrian chic style and beauty prep content immediately.",
    "equestrian_angle": "Preakness Stakes buzz plus CHIO Aachen trending — horse culture has serious momentum right now.",
    "beauty_body_care_angle": "Cannes glow beauty rituals trending; skin prep and luminous look content will perform this week.",
    "cultural_moment": "Cannes Film Festival is at peak cultural saturation — luxury, fashion, beauty all converging.",
    "brand_to_watch": "Dior — Beauty Suite at Cannes plus Hollywood revamp under Anderson signals aggressive brand repositioning."
  },
  "top_trends": [
    {
      "rank": 1,
      "trend_name": "Preakness Stakes Style Moment",
      "category": "Equestrian",
      "virality_score": 8.5,
      "brand_relevance_score": 9.5,
      "brand_relevance_reason": "Preakness is peak equestrian culture — fashion, beauty, and horses collide perfectly for CoBa's Daughter.",
      "signal_sources": [
        "WWD Fashion",
        "Equestrian Calendar"
      ],
      "what_is_it": "Preakness Stakes is 3 days away — horse racing fashion and culture peak moment.",
      "why_it_matters": "Triple Crown season drives massive mainstream equestrian interest and aspirational style content.",
      "heat_level": "Peaking Fast",
      "urgency": "Post Today",
      "window": "72 hours",
      "key_hashtags": [
        "#Preakness",
        "#PreaknessFashion",
        "#HorseRacing",
        "#EquestrianStyle"
      ],
      "content_angle": "The beauty and style ritual of a woman who lives for race day at the track.",
      "tactics": {
        "post_now": [
          "Reel: 'What I wear and how I prep my skin for race day' — elegant, editorial tone.",
          "Carousel: Preakness outfit flatlay with beauty essentials — hat, gloves, SPF, fragrance."
        ],
        "ugc_brief": "Creator gets dressed for Preakness — equestrian chic meets polished beauty routine.",
        "asset_creation": "Editorial flatlay: wide-brim hat, leather gloves, fragrance, SPF on stable-adjacent surface.",
        "seeding": "Seed to equestrian lifestyle creators and horse racing enthusiast communities immediately.",
        "caption_hooks": [
          "Race day is a full ritual. Here's mine.",
          "She dresses for the horse, not the crowd.",
          "Three days to Preakness. Are you ready?"
        ]
      }
    },
    {
      "rank": 2,
      "trend_name": "Cannes Luxury Beauty Glow",
      "category": "Beauty",
      "virality_score": 9.0,
      "brand_relevance_score": 8.5,
      "brand_relevance_reason": "Cannes glamour, skin rituals, and luxury beauty align precisely with CoBa's Daughter's premium positioning.",
      "signal_sources": [
        "WWD Beauty",
        "The Hollywood Reporter",
        "Business of Fashion"
      ],
      "what_is_it": "Cannes Film Festival driving luxury beauty content — Dior Beauty Suite, La Prairie at Carlton Hotel.",
      "why_it_matters": "Cannes is the global pinnacle of aspirational beauty and fashion — audience is fully engaged.",
      "heat_level": "Peaking",
      "urgency": "Post Today",
      "window": "48 hours",
      "key_hashtags": [
        "#Cannes2025",
        "#CannesBeauty",
        "#LuxuryBeauty",
        "#SkinRitual"
      ],
      "content_angle": "Your skin deserves a Cannes-level ritual whether you're at the Croisette or the countryside.",
      "tactics": {
        "post_now": [
          "Reel: 'Cannes-inspired skin prep routine for women who live outdoors and still want the glow.'",
          "Story series: 'Croisette beauty meets countryside girl' — luxury skin ritual content."
        ],
        "ugc_brief": "Creator films her evening skin ritual using golden-hour outdoor lighting — Cannes energy, stable setting.",
        "asset_creation": "Moody golden-light product shot — skincare and fragrance on marble or weathered wood surface.",
        "seeding": "Pitch to luxury beauty editors and Cannes-adjacent lifestyle creators today.",
        "caption_hooks": [
          "Cannes has a beauty suite. You have yours.",
          "The glow doesn't require a red carpet.",
          "Luxury skin ritual, no Croisette required."
        ]
      }
    },
    {
      "rank": 3,
      "trend_name": "Quiet Luxury Equestrian Fashion",
      "category": "Fashion",
      "virality_score": 7.5,
      "brand_relevance_score": 9.5,
      "brand_relevance_reason": "Horse girl aesthetic is trending on YouTube and equestrian chic is CoBa's Daughter's core identity.",
      "signal_sources": [
        "YouTube Equestrian Niche",
        "WWD Fashion"
      ],
      "what_is_it": "Horse girl aesthetic content surging on YouTube and social — western, Icelandic horse, riding style.",
      "why_it_matters": "Organic equestrian aesthetic interest creates receptive audience for CoBa's Daughter's visual world.",
      "heat_level": "Peaking Fast",
      "urgency": "Post Today",
      "window": "This week",
      "key_hashtags": [
        "#HorseGirlAesthetic",
        "#EquestrianChic",
        "#QuietLuxury",
        "#EquestrianStyle"
      ],
      "content_angle": "The horse girl who never stopped — she just upgraded her aesthetic.",
      "tactics": {
        "post_now": [
          "Reel: Morning stable routine shot in quiet luxury aesthetic — no talking, all atmosphere.",
          "Carousel: 'Horse girl, grown up' — heritage fashion pieces flatlay with equestrian props."
        ],
        "ugc_brief": "Creator films golden-hour stable walk in heritage-coded outfit — no performance, pure lifestyle.",
        "asset_creation": "Film on 16mm-style filter: woman leading horse in countryside, heritage leather accessories visible.",
        "seeding": "Target horse girl aesthetic creators with under 200K — highest authenticity signal right now.",
        "caption_hooks": [
          "She never grew out of it. She grew into it.",
          "The aesthetic was always there.",
          "Horse girl is not a phase. It's a lifestyle."
        ]
      }
    },
    {
      "rank": 4,
      "trend_name": "Outdoor Skin Protection SPF",
      "category": "Body Care",
      "virality_score": 7.0,
      "brand_relevance_score": 8.5,
      "brand_relevance_reason": "Equestrian women face harsh outdoor exposure — SPF and skin recovery are urgent, authentic brand territory.",
      "signal_sources": [
        "Cosmopolitan",
        "Allure",
        "WWD Beauty"
      ],
      "what_is_it": "Mineral SPF and Korean Vitamin C serums surging in editorial coverage ahead of summer season.",
      "why_it_matters": "Summer skin protection content is at peak editorial interest — audience actively researching products.",
      "heat_level": "Peaking",
      "urgency": "Post This Week",
      "window": "5 days",
      "key_hashtags": [
        "#SPF",
        "#SkinProtection",
        "#OutdoorSkincare",
        "#GlowySkin",
        "#SummerSkin"
      ],
      "content_angle": "Riding in the sun is non-negotiable. Your skin protection ritual shouldn't be either.",
      "tactics": {
        "post_now": [
          "Carousel: 'Post-ride skin recovery routine' — cleanser, SPF, serum, lip balm, body oil.",
          "Reel: Apply SPF before mounting — show real outdoor skin prep ritual, not vanity table."
        ],
        "ugc_brief": "Creator demonstrates her outdoor skin prep before a morning ride — raw, real, aspirational.",
        "asset_creation": "Flatlay of SPF, vitamin C serum, and recovery balm on stable fence post or saddle pad.",
        "seeding": "Seed to outdoor lifestyle and equestrian skincare niche creators this week.",
        "caption_hooks": [
          "Wind, sun, and saddle. Your skin needs a strategy.",
          "SPF is the most underrated riding essential.",
          "She glows because she protects."
        ]
      }
    },
    {
      "rank": 5,
      "trend_name": "Dior Hollywood Takeover",
      "category": "Pop Culture",
      "virality_score": 8.0,
      "brand_relevance_score": 7.0,
      "brand_relevance_reason": "Dior's aggressive Cannes + Hollywood positioning sets the luxury beauty narrative CoBa's Daughter must respond to.",
      "signal_sources": [
        "Business of Fashion",
        "WWD Beauty"
      ],
      "what_is_it": "Dior executing aggressive cultural takeover — Hollywood editorial plus Cannes Beauty Suite activation.",
      "why_it_matters": "Dior is dominating the aspirational luxury conversation — CoBa's Daughter must carve distinct space.",
      "heat_level": "Peaking",
      "urgency": "Post This Week",
      "window": "7 days",
      "key_hashtags": [
        "#LuxuryBeauty",
        "#HeritageBeauty",
        "#EquestrianLuxury"
      ],
      "content_angle": "Counter-program: heritage luxury rooted in nature and horse culture vs. red carpet performance.",
      "tactics": {
        "post_now": [
          "Reel: 'Not Cannes, not Hollywood — the countryside. Still luxury.' Editorial outdoor beauty content.",
          "Post: Quiet luxury beauty ritual framed against Cannes noise — CoBa's Daughter is the antidote."
        ],
        "ugc_brief": "Creator contrasts red carpet glam with understated equestrian luxury — same confidence, different world.",
        "asset_creation": "Split visual concept: red carpet chaos vs. serene stable sunrise — CoBa's Daughter owns the latter.",
        "seeding": "Engage fashion editors covering Dior at Cannes with CoBa's Daughter's rural luxury alternative narrative.",
        "caption_hooks": [
          "Not every luxury story begins on a red carpet.",
          "The real glamour is in the paddock.",
          "Heritage over hype. Always."
        ]
      }
    },
    {
      "rank": 6,
      "trend_name": "Mental Health Wellness Rituals",
      "category": "Cultural Relevancy",
      "virality_score": 7.0,
      "brand_relevance_score": 8.0,
      "brand_relevance_reason": "Mental Health Awareness Month aligns with CoBa's Daughter's wellness ethos — horses and nature as healing.",
      "signal_sources": [
        "Awareness Calendar",
        "Allure",
        "Cosmopolitan"
      ],
      "what_is_it": "Mental Health Awareness Month driving #selfcare and #wellness content across all platforms.",
      "why_it_matters": "Equine therapy and nature-based wellness are authentic, differentiated angles within the wellness conversation.",
      "heat_level": "Peaking",
      "urgency": "Post This Week",
      "window": "12 days remaining",
      "key_hashtags": [
        "#MentalHealthMonth",
        "#Selfcare",
        "#Wellness",
        "#EquestrianWellness",
        "#HorseTherapy"
      ],
      "content_angle": "The stable is the original wellness retreat. Horses don't lie, and neither does nature.",
      "tactics": {
        "post_now": [
          "Reel: Slow morning stable ritual — grooming, breathing, stillness — framed as mental reset.",
          "Carousel: '5 ways riding heals what no spa can' — emotional, earned, specific."
        ],
        "ugc_brief": "Creator shares what time with her horse does for her mental health — vulnerable, specific, no products.",
        "asset_creation": "Cinematic slow-motion: woman leaning forehead against horse neck — intimate, healing, wordless.",
        "seeding": "Seed to wellness and mental health creator community who have equestrian adjacent audiences.",
        "caption_hooks": [
          "Some therapy doesn't have a waiting room.",
          "She found her stillness in the stable.",
          "Mental health month reminder: go ride."
        ]
      }
    }
  ],
  "brand_launches_now": [
    {
      "brand": "Dior",
      "what": "Dior Beauty Suite activated at Cannes Film Festival — full luxury beauty experience on the Croisette.",
      "why_it_matters": "Dior is owning the luxury beauty conversation at peak cultural moment — sets the aspirational bar.",
      "our_response": "Counter-program with countryside luxury beauty ritual content — same premium, different world.",
      "urgency": "Now"
    },
    {
      "brand": "La Prairie",
      "what": "La Prairie launched luxury cocoon activation inside Carlton Hotel at Cannes.",
      "why_it_matters": "Ultra-premium skincare is claiming experiential luxury territory — CoBa's Daughter should own the outdoor version.",
      "our_response": "Position CoBa's Daughter as the premium skin ritual for women who live outside, not in hotel suites.",
      "urgency": "Now"
    },
    {
      "brand": "Rare Beauty",
      "what": "Rare Beauty launched campaign celebrating diversity of Latinidad — culturally resonant and editorial.",
      "why_it_matters": "Inclusive luxury beauty is gaining editorial momentum — diversity of the equestrian world is underrepresented.",
      "our_response": "Seed diverse equestrian beauty content this week — women of all backgrounds who ride and glow.",
      "urgency": "This Week"
    },
    {
      "brand": "Swatch x Audemars Piguet",
      "what": "Swatch and Audemars Piguet collaboration generating 'most hype ever' for a new watch drop.",
      "why_it_matters": "Heritage luxury collaborations driving massive cultural conversation — validates CoBa's Daughter's heritage positioning.",
      "our_response": "Lean into heritage craft storytelling — the bridle, the boot, the ritual. Same energy as a watch collab.",
      "urgency": "This Week"
    },
    {
      "brand": "Chanel",
      "what": "Chanel partnered with Dia Art Foundation — art-meets-fashion luxury brand positioning move.",
      "why_it_matters": "Chanel is deepening cultural credibility beyond fashion — CoBa's Daughter should pursue similar art or craft angles.",
      "our_response": "Explore equestrian craft as art angle — commission a visual artist to document horse and rider beauty ritual.",
      "urgency": "This Week"
    }
  ],
  "hot_hashtags": [
    {
      "hashtag": "#Preakness",
      "category": "Equestrian",
      "posts_signal": "Rising",
      "how_to_use": "Post equestrian style and beauty prep content for race day — window closes in 72 hours."
    },
    {
      "hashtag": "#HorseGirlAesthetic",
      "category": "Equestrian",
      "posts_signal": "Rising",
      "how_to_use": "Use on atmospheric stable and riding lifestyle content targeting aspirational equestrian audience."
    },
    {
      "hashtag": "#Cannes2025",
      "category": "Pop Culture",
      "posts_signal": "Viral",
      "how_to_use": "Counter-program with outdoor luxury beauty content — countryside vs. Croisette narrative."
    },
    {
      "hashtag": "#EquestrianStyle",
      "category": "Fashion",
      "posts_signal": "Rising",
      "how_to_use": "Anchor all heritage fashion content to this tag while it has organic momentum."
    },
    {
      "hashtag": "#MentalHealthMonth",
      "category": "Cultural Relevancy",
      "posts_signal": "High",
      "how_to_use": "Connect equine therapy and stable wellness rituals to this month's conversation authentically."
    },
    {
      "hashtag": "#SPF",
      "category": "Body Care",
      "posts_signal": "Rising",
      "how_to_use": "Tie outdoor riding SPF content to summer skin protection surge — practical and aspirational angle."
    },
    {
      "hashtag": "#QuietLuxury",
      "category": "Fashion",
      "posts_signal": "High",
      "how_to_use": "Frame every equestrian aesthetic post within quiet luxury visual language — no logos, all texture."
    },
    {
      "hashtag": "#LuxuryBeauty",
      "category": "Beauty",
      "posts_signal": "High",
      "how_to_use": "Use on beauty ritual content to compete for Cannes-adjacent luxury beauty audience this week."
    }
  ],
  "hollywood_pulse": {
    "top_celebrity_moments": [
      "Cannes Film Festival dominating — multiple films, directors, and stars commanding global media attention this week.",
      "Joey King's ladybug French manicure moment trending — fresh spring nail look going viral via The Zoe Report."
    ],
    "top_celebrity_looks": [
      "Joey King — fresh ladybug French manicure in Miu Miu, trending as spring nail inspo right now.",
      "Rita Ora — body glitter worn in a new editorial way, generating beauty look coverage in Allure today."
    ],
    "brand_tie_in_opportunity": "Joey King's Miu Miu French manicure moment — riff on fresh spring nail aesthetics for the equestrian woman who keeps her hands clean and polished despite stable life."
  },
  "equestrian_pulse": {
    "trending_topics": [
      "Preakness Stakes in 3 days — race day style and beauty content window is open now",
      "CHIO Aachen 2025 generating goosebumps content — high-level equestrian sport is culturally visible"
    ],
    "crossover_opportunity": "Preakness Stakes is the perfect runway for equestrian beauty meets fashion — wide-brim hats, glowing skin, heritage leather accessories.",
    "creator_profile": "Female equestrian creator 25-40 with authentic stable life content, aesthetic sensibility, and 20K-150K following — micro has highest trust signal right now."
  },
  "weekly_content_calendar_suggestions": [
    {
      "day": "Monday",
      "theme": "Race Day Beauty Prep",
      "format": "Reel",
      "angle": "Skin prep and style ritual for Preakness — 3 days out countdown energy."
    },
    {
      "day": "Tuesday",
      "theme": "Cannes vs. Countryside",
      "format": "Carousel",
      "angle": "Counter-program Cannes luxury narrative with outdoor-rooted beauty ritual content."
    },
    {
      "day": "Wednesday",
      "theme": "Preakness Day",
      "format": "Reel + Story",
      "angle": "Live Preakness energy — equestrian style, beauty, and race day ritual content."
    },
    {
      "day": "Thursday",
      "theme": "Mental Health + Horses",
      "format": "Reel",
      "angle": "Slow, atmospheric stable wellness content for Mental Health Awareness Month."
    },
    {
      "day": "Friday",
      "theme": "Summer Skin Protection",
      "format": "Carousel",
      "angle": "Post-Preakness pivot to summer riding skin care — SPF, recovery, glow."
    },
    {
      "day": "Saturday",
      "theme": "Horse Girl Aesthetic",
      "format": "Reel",
      "angle": "Golden-hour stable content — quiet luxury, no talking, all atmosphere and texture."
    },
    {
      "day": "Sunday",
      "theme": "Weekly Ritual Reset",
      "format": "Story Series",
      "angle": "Sunday grooming and beauty ritual — the weekend wind-down that starts at the stable."
    }
  ],
  "creator_brief_of_the_week": {
    "concept": "Preakness race day morning ritual — from stable to stands, beauty and style in one aesthetic arc.",
    "target_creator_profile": "Female equestrian or horse racing enthusiast, 25-40, aesthetic feed, authentic stable access, 30K-200K followers.",
    "deliverable": "One 60-90 second Reel documenting morning race day prep — skin routine, outfit, and stable moment before leaving.",
    "hook": "Race day starts before the horses do.",
    "dos": [
      "Show real skin prep including SPF and lip care for outdoor conditions",
      "Include one genuine stable or horse moment — authenticity is non-negotiable"
    ],
    "donts": [
      "Do not make it a haul or product review format — lifestyle narrative only",
      "Do not over-style — quiet luxury means effortless, not curated chaos"
    ]
  },
  "viral_pulse": {
    "viral_products": [
      "SkinCeuticals SPF 50 — Cosmopolitan review driving genuine purchase interest this week.",
      "Therabody LED Mask — two-month test review live now, generating wellness community discussion."
    ],
    "viral_moments": [
      "Dunkin' 48oz Coffee Bucket going nationwide — cultural chaos moment showing scale of viral product demand.",
      "Swatch x Audemars Piguet collab — most hype ever for a watch drop, heritage luxury conversation at peak."
    ],
    "viral_social_trends": [
      "TikTok comments section driving first purchases — comment section is now a conversion tool, not just engagement.",
      "Athlete influencer economy scaling — authentic sports-adjacent creators are outperforming celebrity for brand trust."
    ],
    "community_conversations": [
      "Equestrian women discussing riding small horses normalization — identity and ethics conversation in niche community.",
      "Beauty community debating extreme thinness as beauty ideal — body image and longevity tension is a live conversation."
    ]
  },
  "cultural_events_now": [
    {
      "event": "Preakness Stakes",
      "relevance": "Equestrian culture at mainstream peak — CoBa's Daughter owns race day beauty and style content this week.",
      "hashtags": [
        "#Preakness",
        "#PreaknessFashion",
        "#HorseRacing",
        "#EquestrianChic"
      ],
      "urgency": "Now"
    },
    {
      "event": "Cannes Film Festival",
      "relevance": "Global luxury and beauty conversation peak — counter-program with outdoor heritage luxury narrative.",
      "hashtags": [
        "#Cannes2025",
        "#LuxuryBeauty",
        "#HeritageStyle"
      ],
      "urgency": "Now"
    },
    {
      "event": "Mental Health Awareness Month",
      "relevance": "Equine therapy and nature-based wellness give CoBa's Daughter a unique, authentic wellness voice.",
      "hashtags": [
        "#MentalHealthMonth",
        "#EquestrianWellness",
        "#Selfcare"
      ],
      "urgency": "This Week"
    },
    {
      "event": "Asian American Heritage Month",
      "relevance": "Spotlight K-beauty influence on equestrian skin care ritual — Korean Vitamin C serums trending in editorial.",
      "hashtags": [
        "#AAPIHeritageMonth",
        "#KBeauty",
        "#SkincareRitual"
      ],
      "urgency": "This Month"
    },
    {
      "event": "Belmont Stakes",
      "relevance": "Triple Crown season building — plant content seeds now for Belmont Stakes equestrian coverage in 24 days.",
      "hashtags": [
        "#BelmontStakes",
        "#TripleCrown",
        "#EquestrianStyle"
      ],
      "urgency": "This Month"
    }
  ],
  "trend_watch": {
    "emerging_to_watch": [
      "K-fragrances — WWD Beauty signals K-beauty expanding into fragrance, early signal worth tracking for CoBa's Daughter.",
      "Athlete influencer economy — sports-adjacent authentic creators scaling fast, equestrian athletes are underutilized here."
    ],
    "fading_trends": [
      "Maximalist beauty looks — extreme glam is losing ground to skin-first quiet beauty, stop investing in OTT looks."
    ],
    "predicted_next_week": "Belmont Stakes and Triple Crown narrative will build — equestrian content demand will spike again in 3 weeks, start seeding now."
  },
  "reddit_seeding": [
    {
      "subreddit": "r/Equestrian",
      "thread_topic": "Preakness Stakes race day style and what to wear to the track",
      "why_we_belong": "CoBa's Daughter lives at the intersection of equestrian culture and style — this is core expertise territory.",
      "angle": "Share genuine knowledge about dressing for outdoor racing events — practical style that holds up in the elements.",
      "example_comment_direction": "Speak to the wind, heat, and standing-all-day reality of race day — hat security, footwear that works on grass, skin that doesn't melt.",
      "seed_type": "Share Experience",
      "urgency": "Post Today"
    },
    {
      "subreddit": "r/Horses",
      "thread_topic": "Skin and hair care for women who ride outdoors in all conditions",
      "why_we_belong": "Outdoor riding creates specific skin and hair challenges — this is an authentic, recurring community pain point.",
      "angle": "Share what actually works for sun, wind, and helmet hair after long rides — practical recovery routine knowledge.",
      "example_comment_direction": "Talk about the specific damage from hat and helmet wear on hair, and what genuinely helps repair it without weighing it down.",
      "seed_type": "Answer",
      "urgency": "Post Today"
    },
    {
      "subreddit": "r/SkincareAddiction",
      "thread_topic": "SPF recommendations for outdoor athletes who sweat and are in sun for hours",
      "why_we_belong": "Equestrian outdoor skin exposure is extreme — mineral SPF experience from the saddle is highly credible here.",
      "angle": "Contribute from the perspective of someone who rides outdoors daily — what holds up, what doesn't, what dermatologists actually recommend.",
      "example_comment_direction": "Share that outdoor riding in full sun for hours is as intense as any sport — and that mineral SPF that doesn't pill under helmet straps is a real game-changer.",
      "seed_type": "Share Experience",
      "urgency": "Post Today"
    },
    {
      "subreddit": "r/femalefashionadvice",
      "thread_topic": "Quiet luxury and heritage aesthetic — what brands and pieces are people building wardrobes around",
      "why_we_belong": "Equestrian heritage fashion is one of the founding pillars of quiet luxury — deep expertise to share here.",
      "angle": "Speak to the equestrian roots of quiet luxury — jodhpurs, riding boots, quality leather — as the original heritage aesthetic.",
      "example_comment_direction": "Mention that some of the most enduring quiet luxury pieces trace directly to equestrian tradition — the trench, the boot, the belt — and suggest specific heritage items worth investing in.",
      "seed_type": "Share Experience",
      "urgency": "This Week"
    },
    {
      "subreddit": "r/selfcare",
      "thread_topic": "Mental Health Awareness Month — activities and rituals that genuinely help with anxiety and stress",
      "why_we_belong": "Equine-assisted therapy and time with horses has documented mental health benefits — authentic and evidence-based contribution.",
      "angle": "Share the grounding effect of spending time with horses — presence, breathing, non-verbal connection — as a real mental health tool.",
      "example_comment_direction": "Describe how the focus required around horses naturally quiets anxious thoughts — not mystical, just the practical reality of being present with a large animal.",
      "seed_type": "Validate",
      "urgency": "This Week"
    },
    {
      "subreddit": "r/HorseBack",
      "thread_topic": "What does your post-ride recovery routine look like — body, skin, hair",
      "why_we_belong": "Post-ride body care is a real, daily need for equestrian women — practical skincare and body care expertise belongs here.",
      "angle": "Share a genuine post-ride recovery routine — the order matters, the products matter, and most equestrians are improvising this.",
      "example_comment_direction": "Walk through what actually works after a sweaty outdoor ride: gentle cleanse, rehydrating body oil, lip recovery, and hair treatment — specific textures and formats that make sense after physical outdoor work.",
      "seed_type": "Share Experience",
      "urgency": "This Week"
    }
  ]
}